<?xml version="1.0" encoding="UTF-8"?><record_update>
    <sys_choice action="INSERT_OR_UPDATE" field="action" table="x_snc_devtools_transporter_record" version="3">
        <sys_choice_set action="INSERT_OR_UPDATE">
            <element>action</element>
            <name>x_snc_devtools_transporter_record</name>
            <sys_class_name>sys_choice_set</sys_class_name>
            <sys_created_by>admin</sys_created_by>
            <sys_created_on>2023-12-01 12:24:26</sys_created_on>
            <sys_mod_count>0</sys_mod_count>
            <sys_name>action</sys_name>
            <sys_package display_value="DevTools WORK IN PROGRESS" source="x_snc_devtools">d689f6901bd38450a89720a8ec4bcbfd</sys_package>
            <sys_policy/>
            <sys_scope display_value="DevTools WORK IN PROGRESS">d689f6901bd38450a89720a8ec4bcbfd</sys_scope>
            <sys_update_name>sys_choice_x_snc_devtools_transporter_record_action</sys_update_name>
            <sys_updated_by>admin</sys_updated_by>
            <sys_updated_on>2023-12-01 12:24:26</sys_updated_on>
        </sys_choice_set>
        <sys_choice action="INSERT_OR_UPDATE">
            <dependent_value/>
            <element>action</element>
            <hint/>
            <inactive>false</inactive>
            <label>Insert or Update</label>
            <language>en</language>
            <name>x_snc_devtools_transporter_record</name>
            <sequence>1</sequence>
            <synonyms/>
            <sys_created_by>admin</sys_created_by>
            <sys_created_on>2023-12-01 12:24:26</sys_created_on>
            <sys_domain>global</sys_domain>
            <sys_domain_path>/</sys_domain_path>
            <sys_mod_count>1</sys_mod_count>
            <sys_updated_by>admin</sys_updated_by>
            <sys_updated_on>2023-12-01 15:12:38</sys_updated_on>
            <value>insert_or_update</value>
        </sys_choice>
        <sys_choice action="INSERT_OR_UPDATE">
            <dependent_value/>
            <element>action</element>
            <hint/>
            <inactive>false</inactive>
            <label>Delete</label>
            <language>en</language>
            <name>x_snc_devtools_transporter_record</name>
            <sequence>2</sequence>
            <synonyms/>
            <sys_created_by>admin</sys_created_by>
            <sys_created_on>2023-12-01 12:24:41</sys_created_on>
            <sys_domain>global</sys_domain>
            <sys_domain_path>/</sys_domain_path>
            <sys_mod_count>0</sys_mod_count>
            <sys_updated_by>admin</sys_updated_by>
            <sys_updated_on>2023-12-01 12:24:41</sys_updated_on>
            <value>delete</value>
        </sys_choice>
    </sys_choice>
</record_update>
