<?xml version="1.0" encoding="UTF-8"?><record_update table="sys_push_notif_app_install">
    <sys_push_notif_app_install action="DELETE">
        <active>true</active>
        <last_registered_on>2021-11-27 11:16:40</last_registered_on>
        <sys_class_name>sys_push_notif_app_install</sys_class_name>
        <sys_created_by>admin</sys_created_by>
        <sys_created_on>2021-11-27 11:16:40</sys_created_on>
        <sys_id>9e3fc60a1bcc8d10edf3642aab4bcb13</sys_id>
        <sys_mod_count>0</sys_mod_count>
        <sys_name>CFBE52E699C9A6CE10A9360DC703128EC01DD3D7637C1268E3670B31F777647B</sys_name>
        <sys_package display_value="DevTools WORK IN PROGRESS" source="x_snc_devtools">d689f6901bd38450a89720a8ec4bcbfd</sys_package>
        <sys_policy/>
        <sys_push_application_id display_value="ServiceNow Mobile Application">05ed2fb177002300258da2e2c81061c2</sys_push_application_id>
        <sys_push_platform_id display_value="Apple">20e71f30ff0002009738ffffffffff6b</sys_push_platform_id>
        <sys_scope display_value="DevTools WORK IN PROGRESS">d689f6901bd38450a89720a8ec4bcbfd</sys_scope>
        <sys_update_name>sys_push_notif_app_install_9e3fc60a1bcc8d10edf3642aab4bcb13</sys_update_name>
        <sys_updated_by>admin</sys_updated_by>
        <sys_updated_on>2021-11-27 11:16:40</sys_updated_on>
        <sys_user_id display_value="System Administrator">6816f79cc0a8016401c5a33be04be441</sys_user_id>
        <token>CFBE52E699C9A6CE10A9360DC703128EC01DD3D7637C1268E3670B31F777647B</token>
    </sys_push_notif_app_install>
<sys_update_version action="INSERT_OR_UPDATE">
        <action>DELETE</action>
        <application display_value="DevTools">d689f6901bd38450a89720a8ec4bcbfd</application>
        <file_path/>
        <instance_id>bbdfc83f1ba93910699443f4bd4bcbe7</instance_id>
        <instance_name>wildvancouver</instance_name>
        <name>sys_push_notif_app_install_9e3fc60a1bcc8d10edf3642aab4bcb13</name>
        <payload><![CDATA[<?xml version="1.0" encoding="UTF-8"?><record_update table="sys_push_notif_app_install">
    <sys_push_notif_app_install action="INSERT_OR_UPDATE">
        <active>true</active>
        <last_registered_on>2021-11-27 11:16:40</last_registered_on>
        <sys_class_name>sys_push_notif_app_install</sys_class_name>
        <sys_created_by>admin</sys_created_by>
        <sys_created_on>2021-11-27 11:16:40</sys_created_on>
        <sys_id>9e3fc60a1bcc8d10edf3642aab4bcb13</sys_id>
        <sys_mod_count>0</sys_mod_count>
        <sys_name>CFBE52E699C9A6CE10A9360DC703128EC01DD3D7637C1268E3670B31F777647B</sys_name>
        <sys_package display_value="DevTools WORK IN PROGRESS" source="x_snc_devtools">d689f6901bd38450a89720a8ec4bcbfd</sys_package>
        <sys_policy/>
        <sys_push_application_id display_value="ServiceNow Mobile Application">05ed2fb177002300258da2e2c81061c2</sys_push_application_id>
        <sys_push_platform_id display_value="Apple">20e71f30ff0002009738ffffffffff6b</sys_push_platform_id>
        <sys_scope display_value="DevTools WORK IN PROGRESS">d689f6901bd38450a89720a8ec4bcbfd</sys_scope>
        <sys_update_name>sys_push_notif_app_install_9e3fc60a1bcc8d10edf3642aab4bcb13</sys_update_name>
        <sys_updated_by>admin</sys_updated_by>
        <sys_updated_on>2021-11-27 11:16:40</sys_updated_on>
        <sys_user_id display_value="System Administrator">6816f79cc0a8016401c5a33be04be441</sys_user_id>
        <token>CFBE52E699C9A6CE10A9360DC703128EC01DD3D7637C1268E3670B31F777647B</token>
    </sys_push_notif_app_install>
</record_update>]]></payload>
        <payload_hash>1187541601</payload_hash>
        <record_name>CFBE52E699C9A6CE10A9360DC703128EC01DD3D7637C1268E3670B31F777647B</record_name>
        <reverted_from/>
        <source>35fa3cfb1ba13110063ddc61ab4bcbc6</source>
        <source_table>sys_upgrade_history</source_table>
        <state>current</state>
        <sys_created_by>admin</sys_created_by>
        <sys_created_on>2023-10-04 17:47:53</sys_created_on>
        <sys_id>fb7b70bf1ba13110063ddc61ab4bcb7d</sys_id>
        <sys_mod_count>0</sys_mod_count>
        <sys_recorded_at>18afbcda6470000001</sys_recorded_at>
        <sys_updated_by>admin</sys_updated_by>
        <sys_updated_on>2023-10-04 17:47:53</sys_updated_on>
        <type>Push Notification Installation</type>
        <update_guid>bb7b70bf10a131108e4fe3b04d05187d</update_guid>
        <update_guid_history>bb7b70bf10a131108e4fe3b04d05187d:1187541601</update_guid_history>
    </sys_update_version>
    <sys_metadata_delete action="INSERT_OR_UPDATE">
        <sys_audit_delete/>
        <sys_class_name>sys_metadata_delete</sys_class_name>
        <sys_created_by>admin</sys_created_by>
        <sys_created_on>2024-03-08 13:12:42</sys_created_on>
        <sys_db_object display_value="" name="sys_push_notif_app_install">sys_push_notif_app_install</sys_db_object>
        <sys_id>3adbb75f80b645f493520acf25a9e141</sys_id>
        <sys_metadata>9e3fc60a1bcc8d10edf3642aab4bcb13</sys_metadata>
        <sys_mod_count>0</sys_mod_count>
        <sys_name>CFBE52E699C9A6CE10A9360DC703128EC01DD3D7637C1268E3670B31F777647B</sys_name>
        <sys_package display_value="DevTools" source="x_snc_devtools">d689f6901bd38450a89720a8ec4bcbfd</sys_package>
        <sys_parent/>
        <sys_policy/>
        <sys_scope display_value="DevTools">d689f6901bd38450a89720a8ec4bcbfd</sys_scope>
        <sys_scope_delete display_value="">00add56a207e4bf3800cdb72bd156af9</sys_scope_delete>
        <sys_update_name>sys_push_notif_app_install_9e3fc60a1bcc8d10edf3642aab4bcb13</sys_update_name>
        <sys_update_version display_value="sys_push_notif_app_install_9e3fc60a1bcc8d10edf3642aab4bcb13">fb7b70bf1ba13110063ddc61ab4bcb7d</sys_update_version>
        <sys_updated_by>admin</sys_updated_by>
        <sys_updated_on>2024-03-08 13:12:42</sys_updated_on>
    </sys_metadata_delete>
</record_update>
